bocpd/__init__.py
bocpd/bayesian_models.py
bocpd/cy_offline_changepoint_detection.py
bocpd/generate_data.py
bocpd/hazard_functions.py
bocpd/offline_likelihoods.py
bocpd/online_likelihoods.py
bocpd/priors.py
bocpd-0.0.4.dist-info/LICENSE
bocpd-0.0.4.dist-info/METADATA
bocpd-0.0.4.dist-info/WHEEL
bocpd-0.0.4.dist-info/top_level.txt
bocpd-0.0.4.dist-info/RECORD
