Metadata-Version: 2.1
Name: bocpd
Version: 0.0.4
Summary: Bayesian Online Changepoint Detection
Author-email: Luan Pham <phamquiluan@gmail.com>
License: The MIT License (MIT)
License-File: LICENSE
Requires-Dist: numpy
Requires-Dist: scipy >=1.6.0
Requires-Dist: decorator
Requires-Dist: pytest
Requires-Dist: matplotlib
Requires-Dist: seaborn
Requires-Dist: tqdm
Provides-Extra: dev
Requires-Dist: black ; extra == 'dev'
Requires-Dist: pytest ; extra == 'dev'
Requires-Dist: coverage ; extra == 'dev'
Requires-Dist: pre-commit ; extra == 'dev'
